{"version":1,"resource":"vscode-remote://ssh-remote%2Bcs010b.cs.ucr.edu/home/csmajs/mchen356/4.2/ItemToPurchase.h","entries":[{"id":"WmU6.h","timestamp":1666229352125},{"id":"eRPL.h","timestamp":1666229417943},{"id":"CBPq.h","timestamp":1666229694537},{"id":"OeGQ.h","timestamp":1666229708864},{"id":"IfRQ.h","timestamp":1666229817399},{"id":"rKM8.h","timestamp":1666229831106},{"id":"IxoK.h","timestamp":1666229843088},{"id":"UJz4.h","timestamp":1666229900867},{"id":"TCUl.h","timestamp":1666230059099},{"id":"TH4e.h","timestamp":1666230071863},{"id":"jLfE.h","timestamp":1666230100333},{"id":"qbjY.h","timestamp":1666230378561},{"id":"46mI.h","timestamp":1666230395330},{"id":"V4sG.h","timestamp":1666230423204},{"id":"9A7y.h","timestamp":1666230449647},{"id":"TIPE.h","timestamp":1666230508913},{"id":"3cFX.h","timestamp":1666230527381},{"id":"tGab.h","timestamp":1666230544997},{"id":"VsIr.h","timestamp":1666230555249},{"id":"6K1F.h","timestamp":1666230759886},{"id":"Wo0t.h","timestamp":1666230970310},{"id":"s67y.h","timestamp":1666231178046},{"id":"wxYb.h","timestamp":1666233025127},{"id":"EVad.h","source":"moved.source","timestamp":1666234156742},{"id":"oTk2.h","timestamp":1666285141580},{"id":"XKHy.h","timestamp":1666285228136},{"id":"wOIG.h","timestamp":1666285439130},{"id":"Aec4.h","timestamp":1666285502325},{"id":"w5al.h","timestamp":1666286796416},{"id":"pelg.h","timestamp":1666286814293},{"id":"mLKs.h","timestamp":1666298624719},{"id":"2pjT.h","timestamp":1666306177314},{"id":"fIU9.h","timestamp":1666306283902},{"id":"YIcB.h","timestamp":1666306469198},{"id":"mxQY.h","timestamp":1666306484767},{"id":"9v52.h","source":"undoRedo.source","timestamp":1666306537402},{"id":"5lYk.h","timestamp":1666306827939},{"id":"y39P.h","timestamp":1666306838093},{"id":"xZjQ.h","timestamp":1666307207104}]}