{"version":1,"resource":"vscode-remote://ssh-remote%2Bcs010b.cs.ucr.edu/home/csmajs/mchen356/4.2/main.cpp","entries":[{"id":"7FGe.cpp","timestamp":1666298372390},{"id":"X9g0.cpp","timestamp":1666298555299},{"id":"fSyY.cpp","timestamp":1666302130246},{"id":"9Kq3.cpp","timestamp":1666302236229},{"id":"EnQ7.cpp","timestamp":1666302279139},{"id":"2V0M.cpp","timestamp":1666302416258},{"id":"t1tc.cpp","timestamp":1666302921134},{"id":"16Y8.cpp","timestamp":1666302981878},{"id":"xhj2.cpp","timestamp":1666303551139},{"id":"xoqR.cpp","timestamp":1666303645627},{"id":"JeSM.cpp","timestamp":1666303771419},{"id":"KTpQ.cpp","timestamp":1666303926963},{"id":"NTcS.cpp","timestamp":1666303987239},{"id":"r7IQ.cpp","timestamp":1666304285356},{"id":"560N.cpp","timestamp":1666304326945},{"id":"Qm4P.cpp","timestamp":1666304392029},{"id":"Cphk.cpp","timestamp":1666304924005},{"id":"bLV9.cpp","timestamp":1666304995471},{"id":"ZWKl.cpp","timestamp":1666305108662},{"id":"Ye6K.cpp","timestamp":1666305168659},{"id":"nQpZ.cpp","timestamp":1666305561719},{"id":"jGo4.cpp","timestamp":1666305632479},{"id":"0x9B.cpp","timestamp":1666305666183},{"id":"aZPF.cpp","timestamp":1666305875760},{"id":"gTFd.cpp","timestamp":1666306663847},{"id":"z00E.cpp","timestamp":1666306690043},{"id":"7pIV.cpp","timestamp":1666306795254},{"id":"OVJs.cpp","timestamp":1666306913234},{"id":"p1i3.cpp","timestamp":1666306976464},{"id":"okTa.cpp","timestamp":1666307222770},{"id":"MxQr.cpp","timestamp":1666307626438},{"id":"cDpM.cpp","timestamp":1666307706278},{"id":"xD46.cpp","timestamp":1666308093668},{"id":"qmB8.cpp","timestamp":1666308172286},{"id":"lQjq.cpp","timestamp":1666308571589},{"id":"w03C.cpp","timestamp":1666308670375},{"id":"3VQf.cpp","timestamp":1666308738938},{"id":"2NFi.cpp","timestamp":1666308794307},{"id":"AkPb.cpp","timestamp":1666308896216},{"id":"DpkX.cpp","timestamp":1666308928854},{"id":"TnFA.cpp","timestamp":1666308980977},{"id":"CXEh.cpp","timestamp":1666309055263},{"id":"zNFa.cpp","timestamp":1666309492736},{"id":"OOTQ.cpp","timestamp":1666309567797},{"id":"J6U9.cpp","timestamp":1666309739969},{"id":"gVVX.cpp","timestamp":1666309827399},{"id":"2sO5.cpp","timestamp":1666309890457},{"id":"I0Za.cpp","timestamp":1666310038748},{"id":"uWrF.cpp","timestamp":1666310743785},{"id":"9SON.cpp","timestamp":1666310760952}]}